arguebuf_cli/__init__.py
arguebuf_cli/__main__.py
arguebuf_cli/app.py
arguebuf_cli/graph.py
arguebuf_cli/graph_translator.py
arguebuf_cli/model.py
arguebuf_cli/py.typed
arguebuf_cli/text.py
arguebuf_cli-1.2.1.dist-info/entry_points.txt
arguebuf_cli-1.2.1.dist-info/LICENSE
arguebuf_cli-1.2.1.dist-info/WHEEL
arguebuf_cli-1.2.1.dist-info/METADATA
arguebuf_cli-1.2.1.dist-info/RECORD
