Metadata-Version: 2.1
Name: arguebuf-cli
Version: 1.2.1
Summary: Command line interface for interacting with argument graphs.
Home-page: https://recap.uni-trier.de
License: MIT
Author: Mirko Lenz
Author-email: info@mirko-lenz.de
Requires-Python: >=3.8,<4.0
Classifier: License :: OSI Approved :: MIT License
Classifier: Programming Language :: Python :: 3
Classifier: Programming Language :: Python :: 3.8
Classifier: Programming Language :: Python :: 3.9
Classifier: Programming Language :: Python :: 3.10
Requires-Dist: arguebuf (>=1.1.3,<2.0.0)
Requires-Dist: deepl-pro (>=0.1.4,<0.2.0)
Requires-Dist: typer[all] (>=0.6.1,<0.7.0)
Project-URL: Repository, https://github.com/recap-utr/arguebuf-cli
